MANIFEST.in
README.md
setup.py
filex/__init__.py
filex/filex.py
filex.egg-info/PKG-INFO
filex.egg-info/SOURCES.txt
filex.egg-info/dependency_links.txt
filex.egg-info/top_level.txt